[
  { "_id": "A101", "title": "A1 - ENV + HTML", "course": "RS101" },
  { "_id": "A102", "title": "A2 - CSS + BOOTSTRAP", "course": "RS101" },
  { "_id": "A103", "title": "A3 - JS + REACT", "course": "RS101" },
  { "_id": "A104", "title": "A4 - STATE + REDUX", "course": "RS101" },
  { "_id": "A105", "title": "A5 - NODE + SESSION", "course": "RS101" },
  { "_id": "A106", "title": "A6 - MANGO", "course": "RS101" },


  
  { "_id": "A201", "title": "Aerodynamics Quiz", "course": "RS102" },
  { "_id": "A202", "title": "Flow Analysis", "course": "RS102" },
  { "_id": "A203", "title": "Heating Analysis", "course": "RS102" },
  { "_id": "A301", "title": "Structural Design Task", "course": "RS103" },
  { "_id": "A302", "title": "Orbital Calculations", "course": "RS103" },
  { "_id": "A303", "title": "Systems Engineering Exam", "course": "RS103" }


]